setup.py
semanticnet/DiGraph.py
semanticnet/Graph.py
semanticnet/__init__.py
semanticnet/algorithms.py
semanticnet/operators.py
semanticnet.egg-info/PKG-INFO
semanticnet.egg-info/SOURCES.txt
semanticnet.egg-info/dependency_links.txt
semanticnet.egg-info/requires.txt
semanticnet.egg-info/top_level.txt
test/test_algorithms.py
test/test_cache.py
test/test_graph.py
test/test_operators.py