Metadata-Version: 1.0
Name: semanticnet
Version: 0.2.0
Summary: Small python library to create semantic graphs in JSON.
Home-page: https://github.com/ThibaultReuille/semanticnet
Author: Thibault Reuille
Author-email: thibault@opendns.com
License: UNKNOWN
Platform: UNKNOWN
